glyxtoolms/__init__.py
glyxtoolms/consensus.py
glyxtoolms/deconvolution.py
glyxtoolms/fragmentation.py
glyxtoolms/io.py
glyxtoolms/lib.py
glyxtoolms/masses.py
glyxtoolms/scoring.py
glyxtoolms/tests.py
glyxtoolms/TOPP/ConsensusSearch.py
glyxtoolms/TOPP/ConsensusSearch.ttd
glyxtoolms/TOPP/FeatureExtractor.py
glyxtoolms/TOPP/FeatureExtractor.ttd
glyxtoolms/TOPP/FeatureFinderMS.py
glyxtoolms/TOPP/FeatureFinderMS.ttd
glyxtoolms/TOPP/FileBuilder.py
glyxtoolms/TOPP/FileBuilder.ttd
glyxtoolms/TOPP/FragmentCheck.py
glyxtoolms/TOPP/FragmentCheck.ttd
glyxtoolms/TOPP/FragmentationTypeExtractor.py
glyxtoolms/TOPP/FragmentationTypeExtractor.ttd
glyxtoolms/TOPP/FragmentationTypeFilesplitter.py
glyxtoolms/TOPP/FragmentationTypeFilesplitter.ttd
glyxtoolms/TOPP/GlycanBuilder.py
glyxtoolms/TOPP/GlycanBuilder.ttd
glyxtoolms/TOPP/GlycanScorer.py
glyxtoolms/TOPP/GlycanScorer.ttd
glyxtoolms/TOPP/GlycoDomainViewer.py
glyxtoolms/TOPP/GlycoDomainViewer.ttd
glyxtoolms/TOPP/GlycoIdentificationScore.py
glyxtoolms/TOPP/GlycoIdentificationScore.ttd
glyxtoolms/TOPP/GlycopeptideDigest.py
glyxtoolms/TOPP/GlycopeptideDigest.ttd
glyxtoolms/TOPP/GlycopeptideMatcher.py
glyxtoolms/TOPP/GlycopeptideMatcher.ttd
glyxtoolms/TOPP/GlycopeptideTable.py
glyxtoolms/TOPP/GlycopeptideTable.ttd
glyxtoolms/TOPP/HGIReporter.py
glyxtoolms/TOPP/HGIReporter.ttd
glyxtoolms/TOPP/HexNAcRatio.py
glyxtoolms/TOPP/HexNAcRatio.ttd
glyxtoolms/TOPP/IdentificationDiscriminator.py
glyxtoolms/TOPP/IdentificationDiscriminator.ttd
glyxtoolms/TOPP/IdentificationMerger.py
glyxtoolms/TOPP/IdentificationMerger.ttd
glyxtoolms/TOPP/IdentificationTransfer.py
glyxtoolms/TOPP/IdentificationTransfer.ttd
glyxtoolms/TOPP/OxoniumFilter.py
glyxtoolms/TOPP/OxoniumFilter.ttd
glyxtoolms/TOPP/PdfReporter.py
glyxtoolms/TOPP/PdfReporter.ttd
glyxtoolms/TOPP/PeptideFilter.py
glyxtoolms/TOPP/PeptideFilter.ttd
glyxtoolms/TOPP/PeptideScorer.py
glyxtoolms/TOPP/PeptideScorer.ttd
glyxtoolms-0.1.5.5.dist-info/METADATA
glyxtoolms-0.1.5.5.dist-info/RECORD
glyxtoolms-0.1.5.5.dist-info/WHEEL
glyxtoolms-0.1.5.5.dist-info/entry_points.txt
glyxtoolms-0.1.5.5.dist-info/top_level.txt
